ansys/api/discovery/VERSION
ansys/api/discovery/__init__.py
ansys/api/discovery/py.typed
ansys/api/discovery/v0/__init__.py
ansys/api/discovery/v0/definedvariationstable.proto
ansys/api/discovery/v0/definedvariationstable_pb2.py
ansys/api/discovery/v0/definedvariationstable_pb2.pyi
ansys/api/discovery/v0/definedvariationstable_pb2_grpc.py
ansys/api/discovery/v0/definedvariationstable_pb2_grpc.pyi
ansys/api/discovery/v0/discoverymodels.proto
ansys/api/discovery/v0/discoverymodels_pb2.py
ansys/api/discovery/v0/discoverymodels_pb2.pyi
ansys/api/discovery/v0/discoverymodels_pb2_grpc.py
ansys/api/discovery/v0/discoverymodels_pb2_grpc.pyi
ansys/api/discovery/v0/historytrackparameters.proto
ansys/api/discovery/v0/historytrackparameters_pb2.py
ansys/api/discovery/v0/historytrackparameters_pb2.pyi
ansys/api/discovery/v0/historytrackparameters_pb2_grpc.py
ansys/api/discovery/v0/historytrackparameters_pb2_grpc.pyi
ansys/api/discovery/v0/messaging.proto
ansys/api/discovery/v0/messaging_pb2.py
ansys/api/discovery/v0/messaging_pb2.pyi
ansys/api/discovery/v0/messaging_pb2_grpc.py
ansys/api/discovery/v0/messaging_pb2_grpc.pyi
ansys/api/discovery/v0/monitors.proto
ansys/api/discovery/v0/monitors_pb2.py
ansys/api/discovery/v0/monitors_pb2.pyi
ansys/api/discovery/v0/monitors_pb2_grpc.py
ansys/api/discovery/v0/monitors_pb2_grpc.pyi
ansys/api/discovery/v0/results.proto
ansys/api/discovery/v0/results_pb2.py
ansys/api/discovery/v0/results_pb2.pyi
ansys/api/discovery/v0/results_pb2_grpc.py
ansys/api/discovery/v0/results_pb2_grpc.pyi
ansys/api/discovery/v0/scriptparameters.proto
ansys/api/discovery/v0/scriptparameters_pb2.py
ansys/api/discovery/v0/scriptparameters_pb2.pyi
ansys/api/discovery/v0/scriptparameters_pb2_grpc.py
ansys/api/discovery/v0/scriptparameters_pb2_grpc.pyi
ansys/api/discovery/v0/simulations.proto
ansys/api/discovery/v0/simulations_pb2.py
ansys/api/discovery/v0/simulations_pb2.pyi
ansys/api/discovery/v0/simulations_pb2_grpc.py
ansys_api_discovery-1.0.23.dist-info/licenses/LICENSE
ansys_api_discovery-1.0.23.dist-info/METADATA
ansys_api_discovery-1.0.23.dist-info/WHEEL
ansys_api_discovery-1.0.23.dist-info/entry_points.txt
ansys_api_discovery-1.0.23.dist-info/top_level.txt
ansys_api_discovery-1.0.23.dist-info/RECORD
