Metadata-Version: 2.4
Name: ansys-api-discovery
Version: 1.0.23
Summary: Autogenerated python gRPC interface package for ansys-api-discovery, built on 08:38:19 on 30 January 2026
Home-page: https://github.com/ansys/ansys-api-discovery
Author: ANSYS, Inc.
Author-email: pyansys.core@ansys.com
Maintainer: ANSYS, Inc.
Maintainer-email: pyansys.core@ansys.com
License: MIT
Project-URL: Documentation, https://github.com/ansys/ansys-api-discovery/#readme
Project-URL: Source, https://github.com/ansys/ansys-api-discovery/
Project-URL: Tracker, https://github.com/ansys/ansys-api-discovery/issues/
Requires-Python: >=3.10
License-File: LICENSE
Requires-Dist: grpcio~=1.44
Requires-Dist: protobuf<7,>=3.19
Requires-Dist: ansys-api-geometry==0.4.91
Dynamic: author
Dynamic: author-email
Dynamic: description
Dynamic: description-content-type
Dynamic: home-page
Dynamic: license
Dynamic: license-file
Dynamic: maintainer
Dynamic: maintainer-email
Dynamic: project-url
Dynamic: requires-dist
Dynamic: requires-python
Dynamic: summary
